netbox_juniper_srx/__init__.py
netbox_juniper_srx/api/__init__.py
netbox_juniper_srx/api/serializers.py
netbox_juniper_srx/api/urls.py
netbox_juniper_srx/api/views.py
netbox_juniper_srx/filtersets.py
netbox_juniper_srx/forms.py
netbox_juniper_srx/graphql.py
netbox_juniper_srx/migrations/0001_initial.py
netbox_juniper_srx/migrations/0002_alter_securitypolicy_default_action_and_more.py
netbox_juniper_srx/migrations/0003_securitypolicy_description_securitypolicy_device_and_more.py
netbox_juniper_srx/migrations/0004_securitypolicyrule_comments_securityzone.py
netbox_juniper_srx/migrations/0005_remove_securitypolicy_site_and_more.py
netbox_juniper_srx/migrations/0006_remove_securityzone_default_action.py
netbox_juniper_srx/migrations/0007_remove_securityzone_match_interfaces_and_more.py
netbox_juniper_srx/migrations/__init__.py
netbox_juniper_srx/models.py
netbox_juniper_srx/navigation.py
netbox_juniper_srx/tables.py
netbox_juniper_srx/templates/netbox_juniper_srx/securitypolicy.html
netbox_juniper_srx/templates/netbox_juniper_srx/securitypolicyrule.html
netbox_juniper_srx/templates/netbox_juniper_srx/securityzone.html
netbox_juniper_srx/urls.py
netbox_juniper_srx/views.py
netbox_juniper_srx-0.0.3.dist-info/LICENSE
netbox_juniper_srx-0.0.3.dist-info/WHEEL
netbox_juniper_srx-0.0.3.dist-info/METADATA
netbox_juniper_srx-0.0.3.dist-info/RECORD
