Metadata-Version: 2.1
Name: netbox-juniper-srx
Version: 0.0.3
Summary: Netbox plugin to manage Juniper SRX security configuration objects.
License: Apache 2.0
Author: Calvin Remsburg
Author-email: cremsburg.dev@gmail.com
Requires-Python: >=3.8,<4.0
Classifier: License :: Other/Proprietary License
Classifier: Programming Language :: Python :: 3
Classifier: Programming Language :: Python :: 3.10
Classifier: Programming Language :: Python :: 3.8
Classifier: Programming Language :: Python :: 3.9
